MANIFEST.in
README.md
setup.py
FAVRIP/__init__.py
FAVRIP/denon.py
FAVRIP/favrip.py
FAVRIP.egg-info/PKG-INFO
FAVRIP.egg-info/SOURCES.txt
FAVRIP.egg-info/dependency_links.txt
FAVRIP.egg-info/top_level.txt